setup.cfg
setup.py
src/TracCron.egg-info/PKG-INFO
src/TracCron.egg-info/SOURCES.txt
src/TracCron.egg-info/dependency_links.txt
src/TracCron.egg-info/entry_points.txt
src/TracCron.egg-info/not-zip-safe
src/TracCron.egg-info/top_level.txt
src/traccron/__init__.py
src/traccron/api.py
src/traccron/core.py
src/traccron/history.py
src/traccron/listener.py
src/traccron/scheduler.py
src/traccron/task.py