Metadata-Version: 1.0
Name: TracCron
Version: 0.3dev
Summary: Trac task scheduler  plugin for Trac.
Home-page: http://trac-hacks.org/wiki/TracCronPlugin
Author: Thierry Bressure
Author-email: thierry@bressure.net
License: BSD
Keywords: trac cron scheduler plugin
Platform: UNKNOWN
Classifier: Framework :: Trac
